python_tgdbapi-0.1.0.dist-info/METADATA
python_tgdbapi-0.1.0.dist-info/RECORD
python_tgdbapi-0.1.0.dist-info/WHEEL
python_tgdbapi-0.1.0.dist-info/top_level.txt
tgdbapi/__init__.py
tgdbapi/api.py
tgdbapi/entity.py
tgdbapi/parser.py
