Metadata-Version: 2.1
Name: python-tgdbapi
Version: 0.1.0
Summary: A comprehensive client for the Games DB API
Home-page: http://github.com/mabernardo/python-tgdbapi/
Author: Marcio Bernardo
Author-email: mabernardo@gmail.com
License: MIT License
Platform: any
Classifier: Programming Language :: Python
Classifier: Development Status :: 4 - Beta
Classifier: Natural Language :: English
Classifier: Environment :: Web Environment
Classifier: Intended Audience :: Developers
Classifier: License :: OSI Approved :: Apache Software License
Classifier: Operating System :: OS Independent
Classifier: Topic :: Software Development :: Libraries :: Python Modules
Provides-Extra: testing
Requires-Dist: pytest; extra == 'testing'
